main.py
source_okta/__init__.py
source_okta/components.py
source_okta/config_migration.py
source_okta/manifest.yaml
source_okta/run.py
source_okta/source.py
source_okta/spec.yaml
airbyte_source_okta-0.3.21.dist-info/METADATA
airbyte_source_okta-0.3.21.dist-info/WHEEL
airbyte_source_okta-0.3.21.dist-info/entry_points.txt
airbyte_source_okta-0.3.21.dist-info/RECORD
